RequestsChecker.py
robotframework_requestschecker-2.0.0.dist-info/LICENSE
robotframework_requestschecker-2.0.0.dist-info/METADATA
robotframework_requestschecker-2.0.0.dist-info/WHEEL
robotframework_requestschecker-2.0.0.dist-info/top_level.txt
robotframework_requestschecker-2.0.0.dist-info/RECORD
